{
  "type": "Feature",
  "properties": {
    "gn:asciiname":"Rose Bank",
    "gn:country_code":"VC",
    "gn:dem":95,
    "gn:feature_class":"P",
    "gn:feature_code":"PPL",
    "gn:name":"Rose Bank",
    "gn:population":0,
    "gn:timezone":"America/St_Vincent",
    "iso:country":"VC",
    "wof:name":"Rose Bank",
    "wof:placetype":"locality"
},
  "geometry": {"coordinates":[-61.25825,13.28418],"type":"Point"}
}