{
  "type": "Feature",
  "properties": {
    "gn:asciiname":"London",
    "gn:country_code":"VC",
    "gn:dem":20,
    "gn:feature_class":"P",
    "gn:feature_code":"PPL",
    "gn:name":"London",
    "gn:population":0,
    "gn:timezone":"America/St_Vincent",
    "iso:country":"VC",
    "wof:name":"London",
    "wof:placetype":"locality"
},
  "geometry": {"coordinates":[-61.12514,13.34046],"type":"Point"}
}