{
  "type": "Feature",
  "properties": {
    "gn:admin1_code":"02",
    "gn:asciiname":"Edinboro",
    "gn:country_code":"VC",
    "gn:dem":61,
    "gn:feature_class":"P",
    "gn:feature_code":"PPL",
    "gn:name":"Edinboro",
    "gn:population":0,
    "gn:timezone":"America/St_Vincent",
    "iso:country":"VC",
    "wof:name":"Edinboro",
    "wof:placetype":"locality"
},
  "geometry": {"coordinates":[-61.23644,13.15981],"type":"Point"}
}