{
  "type": "Feature",
  "properties": {
    "gn:asciiname":"Keartons",
    "gn:country_code":"VC",
    "gn:dem":29,
    "gn:feature_class":"P",
    "gn:feature_code":"PPL",
    "gn:name":"Keartons",
    "gn:population":0,
    "gn:timezone":"America/St_Vincent",
    "iso:country":"VC",
    "wof:name":"Keartons",
    "wof:placetype":"locality"
},
  "geometry": {"coordinates":[-61.27268,13.2432],"type":"Point"}
}