{
  "type": "Feature",
  "properties": {
    "gn:admin1_code":"02",
    "gn:asciiname":"Chauncey",
    "gn:country_code":"VC",
    "gn:dem":170,
    "gn:feature_class":"P",
    "gn:feature_code":"PPL",
    "gn:name":"Chauncey",
    "gn:population":0,
    "gn:timezone":"America/St_Vincent",
    "iso:country":"VC",
    "name:ceb_x_preferred":[
        "Chauncey"
    ],
    "name:ces_x_preferred":[
        "Chauncey"
    ],
    "name:deu_x_preferred":[
        "Chauncey"
    ],
    "name:ita_x_preferred":[
        "Chauncey"
    ],
    "name:jpn_x_preferred":[
        "\u30c1\u30e7\u30a6\u30f3\u30b7\u30fc"
    ],
    "name:nld_x_preferred":[
        "Chauncey"
    ],
    "name:pol_x_preferred":[
        "Chauncey"
    ],
    "name:por_x_preferred":[
        "Chauncey"
    ],
    "name:srp_x_preferred":[
        "\u0427\u043e\u043d\u0441\u0438"
    ],
    "name:ukr_x_preferred":[
        "\u0427\u043e\u043d\u0441\u0456"
    ],
    "name:vol_x_preferred":[
        "Chauncey"
    ],
    "wof:name":"Chauncey",
    "wof:placetype":"locality"
},
  "geometry": {"coordinates":[-61.23333,13.16667],"type":"Point"}
}