{
  "type": "Feature",
  "properties": {
    "gn:admin1_code":"05",
    "gn:asciiname":"Hermitage",
    "gn:country_code":"VC",
    "gn:dem":357,
    "gn:feature_class":"P",
    "gn:feature_code":"PPL",
    "gn:name":"Hermitage",
    "gn:population":0,
    "gn:timezone":"America/St_Vincent",
    "iso:country":"VC",
    "wof:name":"Hermitage",
    "wof:placetype":"locality"
},
  "geometry": {"coordinates":[-61.21685,13.24955],"type":"Point"}
}