{
  "type": "Feature",
  "properties": {
    "gn:admin1_code":"05",
    "gn:asciiname":"Hermitage",
    "gn:country_code":"VC",
    "gn:dem":357,
    "gn:feature_class":"P",
    "gn:feature_code":"PPL",
    "gn:name":"Hermitage",
    "gn:population":0,
    "gn:timezone":"America/St_Vincent",
    "iso:country":"VC",
    "name:bre_x_preferred":[
        "Hermitage"
    ],
    "name:ceb_x_preferred":[
        "Hermitage"
    ],
    "name:deu_x_preferred":[
        "Hermitage"
    ],
    "name:fra_x_preferred":[
        "Hermitage"
    ],
    "name:ita_x_preferred":[
        "Hermitage"
    ],
    "name:jpn_x_preferred":[
        "\u30a8\u30eb\u30df\u30bf\u30fc\u30b8\u30e5"
    ],
    "name:lim_x_preferred":[
        "Hermitage"
    ],
    "name:nds_x_preferred":[
        "Hermitage"
    ],
    "name:nld_x_preferred":[
        "Hermitage"
    ],
    "name:pol_x_preferred":[
        "Hermitage"
    ],
    "name:por_x_preferred":[
        "Hermitage"
    ],
    "name:rus_x_preferred":[
        "\u042d\u0440\u043c\u0438\u0442\u0430\u0436"
    ],
    "name:srp_x_preferred":[
        "\u0425\u0435\u0440\u043c\u0438\u0442\u0438\u045f"
    ],
    "name:swe_x_preferred":[
        "Hermitage"
    ],
    "name:tat_x_preferred":[
        "\u042d\u0440\u043c\u0438\u0442\u0430\u0436"
    ],
    "name:ukr_x_preferred":[
        "\u0415\u0440\u043c\u0456\u0442\u0430\u0436"
    ],
    "name:vol_x_preferred":[
        "Hermitage"
    ],
    "wof:name":"Hermitage",
    "wof:placetype":"locality"
},
  "geometry": {"coordinates":[-61.21685,13.24955],"type":"Point"}
}