{
  "type": "Feature",
  "properties": {
    "gn:asciiname":"Cumberland",
    "gn:country_code":"VC",
    "gn:dem":14,
    "gn:feature_class":"P",
    "gn:feature_code":"PPL",
    "gn:name":"Cumberland",
    "gn:population":0,
    "gn:timezone":"America/St_Vincent",
    "iso:country":"VC",
    "name:und_x_variant":[
        "Washilabo"
    ],
    "wof:name":"Cumberland",
    "wof:placetype":"locality"
},
  "geometry": {"coordinates":[-61.25946999999999,13.2666],"type":"Point"}
}