{
  "type": "Feature",
  "properties": {
    "gn:asciiname":"Cumberland",
    "gn:country_code":"VC",
    "gn:dem":14,
    "gn:feature_class":"P",
    "gn:feature_code":"PPL",
    "gn:name":"Cumberland",
    "gn:population":0,
    "gn:timezone":"America/St_Vincent",
    "iso:country":"VC",
    "name:ang_x_preferred":[
        "Cumbraland"
    ],
    "name:azb_x_preferred":[
        "\u06a9\u0627\u0645\u0628\u0631\u0644\u0646\u062f"
    ],
    "name:bel_x_preferred":[
        "\u041a\u0430\u043c\u0431\u0435\u0440\u043b\u0435\u043d\u0434"
    ],
    "name:bre_x_preferred":[
        "Cumberland"
    ],
    "name:bul_x_preferred":[
        "\u041a\u044a\u043c\u0431\u044a\u0440\u043b\u0430\u043d\u0434"
    ],
    "name:cat_x_preferred":[
        "Cumberland"
    ],
    "name:ceb_x_preferred":[
        "Cumberland"
    ],
    "name:ces_x_preferred":[
        "Cumberland"
    ],
    "name:dan_x_preferred":[
        "Cumberland"
    ],
    "name:deu_x_preferred":[
        "Cumberland"
    ],
    "name:epo_x_preferred":[
        "Cumberland"
    ],
    "name:fas_x_preferred":[
        "\u06a9\u0627\u0645\u0628\u0631\u0644\u0646\u062f"
    ],
    "name:fin_x_preferred":[
        "Cumberland"
    ],
    "name:fra_x_preferred":[
        "Cumberland"
    ],
    "name:ind_x_preferred":[
        "Cumberland"
    ],
    "name:ita_x_preferred":[
        "Cumberland"
    ],
    "name:jpn_x_preferred":[
        "\u30ab\u30f3\u30d0\u30fc\u30e9\u30f3\u30c9"
    ],
    "name:kor_x_preferred":[
        "\ucef4\ubc8c\ub79c\ub4dc"
    ],
    "name:nld_x_preferred":[
        "Cumberland"
    ],
    "name:pol_x_preferred":[
        "Cumberland"
    ],
    "name:por_x_preferred":[
        "Cumberland"
    ],
    "name:ron_x_preferred":[
        "Cumberland"
    ],
    "name:rus_x_preferred":[
        "\u041a\u0430\u043c\u0431\u0435\u0440\u043b\u0435\u043d\u0434"
    ],
    "name:slk_x_preferred":[
        "Cumberland"
    ],
    "name:spa_x_preferred":[
        "Cumberland"
    ],
    "name:swe_x_preferred":[
        "Cumberland"
    ],
    "name:ukr_x_preferred":[
        "\u041a\u0430\u043c\u0431\u0435\u0440\u043b\u0435\u043d\u0434"
    ],
    "name:und_x_variant":[
        "Washilabo"
    ],
    "name:urd_x_preferred":[
        "\u06a9\u0645\u0628\u0631\u0644\u06cc\u0646\u0688"
    ],
    "name:zho_x_preferred":[
        "\u574e\u4f2f\u862d"
    ],
    "wof:name":"Cumberland",
    "wof:placetype":"locality"
},
  "geometry": {"coordinates":[-61.25946999999999,13.2666],"type":"Point"}
}