{
  "type": "Feature",
  "properties": {
    "gn:admin1_code":"03",
    "gn:asciiname":"Wallibou",
    "gn:cc2":"VC",
    "gn:country_code":"VC",
    "gn:dem":42,
    "gn:feature_class":"P",
    "gn:feature_code":"PPL",
    "gn:name":"Wallibou",
    "gn:population":0,
    "gn:timezone":"America/St_Vincent",
    "iso:country":"VC",
    "name:und_x_variant":[
        "Wallibu",
        "Wallibou"
    ],
    "wof:name":"Wallibou",
    "wof:placetype":"locality"
},
  "geometry": {"coordinates":[-61.23221,13.31151],"type":"Point"}
}