{
  "type": "Feature",
  "properties": {
    "gn:admin1_code":"03",
    "gn:asciiname":"Rosehall",
    "gn:country_code":"VC",
    "gn:dem":341,
    "gn:feature_class":"P",
    "gn:feature_code":"PPL",
    "gn:name":"Rosehall",
    "gn:population":0,
    "gn:timezone":"America/St_Vincent",
    "iso:country":"VC",
    "name:eus_x_preferred":[
        "Rosehall"
    ],
    "name:swe_x_preferred":[
        "Rosehall"
    ],
    "wof:name":"Rosehall",
    "wof:placetype":"locality"
},
  "geometry": {"coordinates":[-61.24228000000001,13.27255],"type":"Point"}
}