{
  "type": "Feature",
  "properties": {
    "gn:admin1_code":"01",
    "gn:asciiname":"Chapmans",
    "gn:country_code":"VC",
    "gn:dem":18,
    "gn:feature_class":"P",
    "gn:feature_code":"PPL",
    "gn:name":"Chapmans",
    "gn:population":0,
    "gn:timezone":"America/St_Vincent",
    "iso:country":"VC",
    "wof:name":"Chapmans",
    "wof:placetype":"locality"
},
  "geometry": {"coordinates":[-61.11724,13.29228],"type":"Point"}
}