{
  "type": "Feature",
  "properties": {
    "gn:admin1_code":"02",
    "gn:asciiname":"Buccament",
    "gn:country_code":"VC",
    "gn:dem":9,
    "gn:feature_class":"P",
    "gn:feature_code":"PPL",
    "gn:name":"Buccament",
    "gn:population":0,
    "gn:timezone":"America/St_Vincent",
    "iso:country":"VC",
    "wof:name":"Buccament",
    "wof:placetype":"locality"
},
  "geometry": {"coordinates":[-61.26681,13.19328],"type":"Point"}
}